tex2im/__init__.py
tex2im-2.5.1.dist-info/METADATA
tex2im-2.5.1.dist-info/WHEEL
tex2im-2.5.1.dist-info/entry_points.txt
tex2im-2.5.1.dist-info/licenses/LICENSE.md
tex2im-2.5.1.dist-info/RECORD
