Metadata-Version: 2.4
Name: tex2im
Version: 2.5.1
Summary: Create images from latex snippets.
Author-email: CD Clark III <clifton.clark@gmail.com>
License-File: LICENSE.md
Classifier: Programming Language :: Python :: 3 :: Only
Classifier: Programming Language :: Python :: 3.8
Classifier: Programming Language :: Python :: 3.9
Classifier: Programming Language :: Python :: 3.10
Classifier: Programming Language :: Python :: 3.11
Classifier: Programming Language :: Python :: 3.12
Classifier: Programming Language :: Python :: 3.13
Classifier: Programming Language :: Python :: 3.14
Requires-Python: >=3.8
Requires-Dist: typer>=0.12.5
